{"ongoing_trials": {}, "hyperparameters": {"space": [{"class_name": "Int", "config": {"name": "encoding_dim", "default": null, "conditions": [], "min_value": 2, "max_value": 5, "step": 1, "sampling": "linear"}}, {"class_name": "Float", "config": {"name": "l2_reg", "default": 1e-06, "conditions": [], "min_value": 1e-06, "max_value": 0.01, "step": null, "sampling": "log"}}, {"class_name": "Int", "config": {"name": "units1", "default": null, "conditions": [], "min_value": 16, "max_value": 98, "step": 16, "sampling": "linear"}}, {"class_name": "Int", "config": {"name": "units2", "default": null, "conditions": [], "min_value": 16, "max_value": 32, "step": 8, "sampling": "linear"}}], "values": {"encoding_dim": 2, "l2_reg": 1e-06, "units1": 16, "units2": 16}}, "start_order": ["0000", "0001", "0002", "0003", "0004", "0005", "0006", "0007", "0008", "0009"], "end_order": ["0000", "0001", "0002", "0003", "0004", "0005", "0006", "0007", "0008", "0009"], "run_times": {"0000": 1, "0001": 1, "0002": 1, "0003": 1, "0004": 1, "0005": 1, "0006": 1, "0007": 1, "0008": 1, "0009": 1}, "retry_queue": [], "seed": 1439, "seed_state": 1471, "tried_so_far": ["7c540830fb0df48001a837ab826e9197", "ee732964b6e85ffb0c198f91be0da39d", "1adeafb058b6a9eb3789ce7ad960dd1c", "fd763e332cb216d618d16d0c183b0e58", "eb5f927d25d15100369e05580f40605b", "26089a689108a970a84b3812fafb7952", "abdf6b441314a8339fa0db37e6591fa5", "f72714f88224c2f581775529222e1eec", "967e845bfdda6c727558b313a4bdb794", "cf5d7274cd372222a61ab50462c90db5"], "id_to_hash": {"0000": "f72714f88224c2f581775529222e1eec", "0001": "7c540830fb0df48001a837ab826e9197", "0002": "cf5d7274cd372222a61ab50462c90db5", "0003": "eb5f927d25d15100369e05580f40605b", "0004": "ee732964b6e85ffb0c198f91be0da39d", "0005": "967e845bfdda6c727558b313a4bdb794", "0006": "1adeafb058b6a9eb3789ce7ad960dd1c", "0007": "abdf6b441314a8339fa0db37e6591fa5", "0008": "fd763e332cb216d618d16d0c183b0e58", "0009": "26089a689108a970a84b3812fafb7952"}, "display": {"search_start": null, "trial_start": {}, "trial_number": {}}, "hyperband_iterations": 1, "max_epochs": 5, "min_epochs": 1, "factor": 3, "brackets": [{"bracket_num": 0, "rounds": [[{"past_id": null, "id": "0007"}, {"past_id": null, "id": "0008"}, {"past_id": null, "id": "0009"}]]}], "current_bracket": 0, "current_iteration": 0}