{"ongoing_trials": {}, "hyperparameters": {"space": [{"class_name": "Int", "config": {"name": "encoding_dim", "default": null, "conditions": [], "min_value": 2, "max_value": 5, "step": 1, "sampling": "linear"}}, {"class_name": "Float", "config": {"name": "l2_reg", "default": 1e-06, "conditions": [], "min_value": 1e-06, "max_value": 0.01, "step": null, "sampling": "log"}}, {"class_name": "Int", "config": {"name": "units1", "default": null, "conditions": [], "min_value": 16, "max_value": 98, "step": 16, "sampling": "linear"}}, {"class_name": "Int", "config": {"name": "units2", "default": null, "conditions": [], "min_value": 16, "max_value": 32, "step": 8, "sampling": "linear"}}], "values": {"encoding_dim": 2, "l2_reg": 1e-06, "units1": 16, "units2": 16}}, "start_order": ["0000", "0001", "0002", "0003", "0004", "0005", "0006", "0007", "0008", "0009"], "end_order": ["0000", "0001", "0002", "0003", "0004", "0005", "0006", "0007", "0008", "0009"], "run_times": {"0000": 1, "0001": 1, "0002": 1, "0003": 1, "0004": 1, "0005": 1, "0006": 1, "0007": 1, "0008": 1, "0009": 1}, "retry_queue": [], "seed": 3477, "seed_state": 3509, "tried_so_far": ["26276ecc18db5f797770987ba75d3a19", "5b40e63f2d52b6df08b5bcda3adc45b9", "068c30f04b69905426e2ffecd8c9b472", "5a92722187521cbedbe56b9b243543db", "7b46c4eeef03b5d2b47da071a135cd6c", "b0b5819429a273a4e36ec4012716e299", "7e8256c6cee4817b59580b0af5db4f23", "825d3d2eefe251ef985fd1fa4a52b555", "6a34601ae2093c45b02e14eb4b6aa0e3", "de1ff99a5829ca31f383de2ad3bd6ebf"], "id_to_hash": {"0000": "26276ecc18db5f797770987ba75d3a19", "0001": "5b40e63f2d52b6df08b5bcda3adc45b9", "0002": "6a34601ae2093c45b02e14eb4b6aa0e3", "0003": "7e8256c6cee4817b59580b0af5db4f23", "0004": "825d3d2eefe251ef985fd1fa4a52b555", "0005": "7b46c4eeef03b5d2b47da071a135cd6c", "0006": "068c30f04b69905426e2ffecd8c9b472", "0007": "5a92722187521cbedbe56b9b243543db", "0008": "de1ff99a5829ca31f383de2ad3bd6ebf", "0009": "b0b5819429a273a4e36ec4012716e299"}, "display": {"search_start": null, "trial_start": {}, "trial_number": {}}, "hyperband_iterations": 1, "max_epochs": 5, "min_epochs": 1, "factor": 3, "brackets": [{"bracket_num": 0, "rounds": [[{"past_id": null, "id": "0007"}, {"past_id": null, "id": "0008"}, {"past_id": null, "id": "0009"}]]}], "current_bracket": 0, "current_iteration": 0}