{"ongoing_trials": {}, "hyperparameters": {"space": [{"class_name": "Int", "config": {"name": "encoding_dim", "default": null, "conditions": [], "min_value": 2, "max_value": 5, "step": 1, "sampling": "linear"}}, {"class_name": "Float", "config": {"name": "l2_reg", "default": 1e-06, "conditions": [], "min_value": 1e-06, "max_value": 0.01, "step": null, "sampling": "log"}}, {"class_name": "Int", "config": {"name": "units1", "default": null, "conditions": [], "min_value": 16, "max_value": 98, "step": 16, "sampling": "linear"}}, {"class_name": "Int", "config": {"name": "units2", "default": null, "conditions": [], "min_value": 16, "max_value": 32, "step": 8, "sampling": "linear"}}], "values": {"encoding_dim": 2, "l2_reg": 1e-06, "units1": 16, "units2": 16}}, "start_order": ["0000", "0001", "0002", "0003", "0004", "0005", "0006", "0007", "0008", "0009"], "end_order": ["0000", "0001", "0002", "0003", "0004", "0005", "0006", "0007", "0008", "0009"], "run_times": {"0000": 1, "0001": 1, "0002": 1, "0003": 1, "0004": 1, "0005": 1, "0006": 1, "0007": 1, "0008": 1, "0009": 1}, "retry_queue": [], "seed": 7166, "seed_state": 7198, "tried_so_far": ["3e9fd6b97820da22346e109876f6ae35", "e40ab84269d9dbed0de3a565368134df", "b18d4e62d39a0b354060f04c29b5dc8e", "34bff032a9607231015f7870e4215bb5", "358bfe719df249d23cd00e6038447342", "9321423650a8391bf26b324de5ba9629", "cdb8ec903451ba25a36514668014a6cf", "0886bc81741ac158f2b2bdc9616da4be", "d513243dd7c644f851a899c6b62d3eca", "56e891b8e48022a02eac083c9fcf15e0"], "id_to_hash": {"0000": "9321423650a8391bf26b324de5ba9629", "0001": "0886bc81741ac158f2b2bdc9616da4be", "0002": "cdb8ec903451ba25a36514668014a6cf", "0003": "34bff032a9607231015f7870e4215bb5", "0004": "358bfe719df249d23cd00e6038447342", "0005": "d513243dd7c644f851a899c6b62d3eca", "0006": "e40ab84269d9dbed0de3a565368134df", "0007": "56e891b8e48022a02eac083c9fcf15e0", "0008": "b18d4e62d39a0b354060f04c29b5dc8e", "0009": "3e9fd6b97820da22346e109876f6ae35"}, "display": {"search_start": null, "trial_start": {}, "trial_number": {}}, "hyperband_iterations": 1, "max_epochs": 5, "min_epochs": 1, "factor": 3, "brackets": [{"bracket_num": 0, "rounds": [[{"past_id": null, "id": "0007"}, {"past_id": null, "id": "0008"}, {"past_id": null, "id": "0009"}]]}], "current_bracket": 0, "current_iteration": 0}